__init__.py
terminal_colors.py
basic_term_colors-1.1.0.dist-info/LICENSE
basic_term_colors-1.1.0.dist-info/METADATA
basic_term_colors-1.1.0.dist-info/WHEEL
basic_term_colors-1.1.0.dist-info/top_level.txt
basic_term_colors-1.1.0.dist-info/RECORD
