Metadata-Version: 2.1
Name: basic_term_colors
Version: 1.1.0
Summary: A small package to color/format your terminal
Author: Patrick Dumford
Classifier: Programming Language :: Python :: 3
Classifier: License :: OSI Approved :: MIT License
Classifier: Operating System :: OS Independent
Requires-Python: >=3.8
License-File: LICENSE
